streamlit_l7vp/__init__.py
streamlit_l7vp-0.0.1.dist-info/LICENSE
streamlit_l7vp-0.0.1.dist-info/METADATA
streamlit_l7vp-0.0.1.dist-info/WHEEL
streamlit_l7vp-0.0.1.dist-info/top_level.txt
streamlit_l7vp-0.0.1.dist-info/RECORD
