Metadata-Version: 2.1
Name: streamlit-l7vp
Version: 0.0.1
Summary: Streamlit Component for rendering L7VP maps
Home-page: https://github.com/lvisei/streamlit-l7vp
Author: lvisei
Author-email: yunji.me@outlook.com
License: Apache-2.0
Keywords: Streamlit,L7VP,PyL7VP,visualization,map,geospatial visualization,geospatial analysis
Platform: UNKNOWN
Classifier: Environment :: Console
Classifier: Intended Audience :: Developers
Classifier: License :: OSI Approved :: Apache Software License
Classifier: Operating System :: OS Independent
Classifier: Programming Language :: Python
Classifier: Programming Language :: Python :: 3
Classifier: Programming Language :: Python :: 3.7
Classifier: Programming Language :: Python :: 3.8
Classifier: Programming Language :: Python :: 3.9
Classifier: Topic :: Software Development :: Libraries
License-File: LICENSE
Requires-Dist: streamlit (>=0.79)
Requires-Dist: pyl7vp
